pstream/__init__.py
pstream/errors.py
pstream/_async/__init__.py
pstream/_async/async_stream.py
pstream/_async/functors.py
pstream/_async/util.py
pstream/_sync/__init__.py
pstream/_sync/stream.py
pstream/_sync/util.py
tests/__init__.py
tests/integrations.py
tests/_async/__init__.py
tests/_async/test_async_stream.py
tests/_async/test_async_stream_2.py
tests/_async/test_chain.py
tests/_async/test_count.py
tests/_async/test_distinct.py
tests/_async/test_distinct_with.py
tests/_async/test_enumerate.py
tests/_async/test_errors.py
tests/_async/test_filter.py
tests/_async/test_filter_false.py
tests/_async/test_flatten.py
tests/_async/test_for_each.py
tests/_async/test_group_by.py
tests/_async/test_inspect.py
tests/_async/test_internals.py
tests/_async/test_iterator.py
tests/_async/test_map.py
tests/_async/test_pool.py
tests/_async/test_reduce.py
tests/_async/test_repeat.py
tests/_async/test_repeat_with.py
tests/_async/test_reverse.py
tests/_async/test_shim.py
tests/_async/test_skip.py
tests/_async/test_skip_while.py
tests/_async/test_sort.py
tests/_async/test_sort_with.py
tests/_async/test_step_by.py
tests/_async/test_take.py
tests/_async/test_take_while.py
tests/_async/test_tee.py
tests/_async/test_zip.py
tests/_async/utils.py
tests/sync/__init__.py
tests/sync/test_stream.py
pstream-0.0.27.dist-info/LICENSE
pstream-0.0.27.dist-info/METADATA
pstream-0.0.27.dist-info/WHEEL
pstream-0.0.27.dist-info/top_level.txt
pstream-0.0.27.dist-info/RECORD
