Metadata-Version: 2.1
Name: pstream
Version: 0.0.27
Summary: Provides a Stream and AsyncStream for composing fluent lazily evaluated, sync/async fusion, iterators.
Home-page: https://github.com/christopher-henderson/pstream
Author: Christopher Henderson
Author-email: chris@chenderson.org
License: UNKNOWN
Platform: UNKNOWN
Classifier: Programming Language :: Python :: 2
Classifier: Programming Language :: Python :: 3
Classifier: License :: OSI Approved :: MIT License
Classifier: Operating System :: OS Independent
Requires-Python: >=2.7.*, !=3.0.*, !=3.1.*, !=3.2.*, !=3.3.*, !=3.4.*, !=3.5.*, <4
Requires-Dist: future (>=0.18.2)
